quote_image_generator/__init__.py
quote_image_generator/generator.py
quote_image_generator/image_draw.py
quote_image_generator/pipelines/__init__.py
quote_image_generator/pipelines/background.py
quote_image_generator/pipelines/base.py
quote_image_generator/pipelines/entities.py
quote_image_generator/pipelines/grid.py
quote_image_generator/pipelines/image.py
quote_image_generator/pipelines/text.py
quote_image_generator/processors/__init__.py
quote_image_generator/processors/emoji.py
quote_image_generator/processors/entities.py
quote_image_generator/processors/text.py
quote_image_generator/types.py
quote_image_generator-0.1.2.dist-info/LICENSE
quote_image_generator-0.1.2.dist-info/METADATA
quote_image_generator-0.1.2.dist-info/WHEEL
quote_image_generator-0.1.2.dist-info/RECORD
